websockets_actions/__init__.py
websockets_actions/broadcast/__init__.py
websockets_actions/broadcast/manager.py
websockets_actions/fastapi/__init__.py
websockets_actions/fastapi/actions.py
websockets_actions/fastapi/endpoints.py
websockets_actions/starlette/__init__.py
websockets_actions/starlette/actions.py
websockets_actions/starlette/mixin.py
websockets_actions-0.3.1.dist-info/WHEEL
websockets_actions-0.3.1.dist-info/METADATA
websockets_actions-0.3.1.dist-info/RECORD
